setup.cfg
setup.py
dp2ppgen/__init__.py
dp2ppgen/dp2ppgen.py
dp2ppgen/footer.txt
dp2ppgen/header.txt
dp2ppgen.egg-info/PKG-INFO
dp2ppgen.egg-info/SOURCES.txt
dp2ppgen.egg-info/dependency_links.txt
dp2ppgen.egg-info/entry_points.txt
dp2ppgen.egg-info/requires.txt
dp2ppgen.egg-info/top_level.txt