Metadata-Version: 1.1
Name: dp2ppgen
Version: 0.2.0
Summary: Translates pgdp.org formatted text files into ppgen syntax.
Home-page: https://github.com/davem2/dp2ppgen
Author: David Maranhao
Author-email: david.maranhao@gmail.com
License: MIT
Download-URL: https://github.com/davem2/dp2ppgen/tarball/0.2.0
Keywords: text,processing,book,ebook,gutenberg,distributedproofreaders
Platform: UNKNOWN
Classifier: Environment :: Console
Classifier: Intended Audience :: Developers
Classifier: License :: OSI Approved :: MIT License
Classifier: Operating System :: OS Independent
Classifier: Programming Language :: Python
Classifier: Programming Language :: Python :: 3 :: Only
Classifier: Topic :: Text Processing
Classifier: Topic :: Text Processing :: Markup
